rlsmorph/__init__.py
rlsmorph-0.1.0.dist-info/LICENSE
rlsmorph-0.1.0.dist-info/METADATA
rlsmorph-0.1.0.dist-info/WHEEL
rlsmorph-0.1.0.dist-info/top_level.txt
rlsmorph-0.1.0.dist-info/RECORD
