Metadata-Version: 2.1
Name: rlsmorph
Version: 0.1.0
Author-email: Mark Mayerfeld <mark.m.mayerfeld@gmail.com>
License: MIT License
Project-URL: repository, https://github.com/RakitaLabSoftware/rlsmorph
Requires-Python: >=3.11
License-File: LICENSE
Requires-Dist: torch (>=2.0)
Requires-Dist: torchvision
Requires-Dist: timm
Requires-Dist: matplotlib
Requires-Dist: opencv-contrib-python
Requires-Dist: kornia
Requires-Dist: rich
Requires-Dist: rlsvision
Provides-Extra: dev
Requires-Dist: pytest ; extra == 'dev'
Requires-Dist: black ; extra == 'dev'
Requires-Dist: isort ; extra == 'dev'
Requires-Dist: build ; extra == 'dev'
Provides-Extra: ipy
Requires-Dist: ipykernel ; extra == 'ipy'
Requires-Dist: ipython ; extra == 'ipy'
Requires-Dist: ipython-genutils ; extra == 'ipy'
Requires-Dist: ipywidgets ; extra == 'ipy'
Requires-Dist: jupyter ; extra == 'ipy'
Requires-Dist: jupyter-client ; extra == 'ipy'
Requires-Dist: jupyter-console ; extra == 'ipy'
Requires-Dist: jupyter-core ; extra == 'ipy'
Requires-Dist: jupyterlab-pygments ; extra == 'ipy'
Requires-Dist: jupyterlab-widgets ; extra == 'ipy'
